tomato_mcc/__init__.py
tomato_mcc-2.1.0.dist-info/licenses/LICENSE
tomato_mcc-2.1.0.dist-info/METADATA
tomato_mcc-2.1.0.dist-info/WHEEL
tomato_mcc-2.1.0.dist-info/top_level.txt
tomato_mcc-2.1.0.dist-info/RECORD
