Metadata-Version: 2.4
Name: tomato-mcc
Version: 2.1.0
Summary: This package is a part of tomato, made for automation of MCC DAQ temperature loggers (ME-Redlab, Digilent).
Author-email: Peter Kraus <peter.kraus@ceramics.tu-berlin.de>
Project-URL: Repository, https://github.com/dgbowl/tomato-mcc
Project-URL: Issues, https://github.com/dgbowl/tomato-mcc/issues
Classifier: Development Status :: 3 - Alpha
Classifier: License :: OSI Approved :: GNU General Public License v3 or later (GPLv3+)
Classifier: Programming Language :: Python :: 3.9
Classifier: Programming Language :: Python :: 3.10
Classifier: Programming Language :: Python :: 3.11
Classifier: Programming Language :: Python :: 3.12
Classifier: Operating System :: Microsoft :: Windows
Requires-Python: >=3.9
License-File: LICENSE
Requires-Dist: mcculw>=1.0.0; platform_system == "Windows"
Requires-Dist: tomato>=2.1rc3
Provides-Extra: testing
Requires-Dist: pytest; extra == "testing"
Dynamic: license-file
